{
    "322e18a4-ef00-4d0f-a827-2e3e569f4482": {
        "id": "322e18a4-ef00-4d0f-a827-2e3e569f4482",
        "name": "Google Search",
        "keyword": "g",
        "cmd": "https://google.com/search?q=%s",
        "icon": "/usr/share/ulauncher/media/google-search-icon.png",
        "is_default_search": true,
        "run_without_argument": false,
        "added": 1577497123.2368355
    },
    "7b41df20-dd48-4784-b018-065bc397188d": {
        "id": "7b41df20-dd48-4784-b018-065bc397188d",
        "name": "Stack Overflow",
        "keyword": "so",
        "cmd": "http://stackoverflow.com/search?q=%s",
        "icon": "/usr/share/ulauncher/media/stackoverflow-icon.svg",
        "is_default_search": true,
        "run_without_argument": false,
        "added": 1577497123.237029
    },
    "4175809a-061e-4da2-8559-a0f614677c50": {
        "id": "4175809a-061e-4da2-8559-a0f614677c50",
        "name": "Wikipedia",
        "keyword": "wiki",
        "cmd": "https://en.wikipedia.org/wiki/%s",
        "icon": "/usr/share/ulauncher/media/wikipedia-icon.png",
        "is_default_search": true,
        "run_without_argument": false,
        "added": 1577497123.237201
    }
}